{
  "lastUpdated": "2026-03-27T01:40:00Z",
  "summary": "Matchly AI: Global Data Feed - Part 1. Focus on International and Americas.",
  "matches": [
    {
      "id": "match_2026_wc_001",
      "league": "World Cup Qualifiers - Inter-Confederation",
      "homeTeam": "Bolivia",
      "awayTeam": "Suriname",
      "date": "2026-03-27",
      "time": "In Play",
      "prediction": {
        "mainPick": "Draw",
        "odds": "2.27",
        "overUnder": "2.5 Under",
        "btts": "No",
        "predictedScore": "0-0",
        "corners": "7.5 Under",
        "cards": "3.5 Over",
        "confidence": 65
      },
      "analysis": "Early stages of the match with both teams playing defensively. A low-scoring draw is highly probable.",
      "result": "pending",
      "vip": false,
      "adUnlock": false,
      "isDailyPick": false
    },
    {
      "id": "match_2026_par_001",
      "league": "Paraguay Primera Division - Apertura",
      "homeTeam": "CD Recoleta",
      "awayTeam": "Rubio Nu",
      "date": "2026-03-27",
      "time": "02:00",
      "prediction": {
        "mainPick": "Draw",
        "odds": "2.77",
        "overUnder": "2.5 Under",
        "btts": "Yes",
        "predictedScore": "1-1",
        "corners": "9.5 Over",
        "cards": "4.5 Over",
        "confidence": 70
      },
      "analysis": "Two defensive-minded sides in the Paraguayan league. Expect a tight encounter with a likely draw.",
      "result": "pending",
      "vip": true,
      "adUnlock": false,
      "isDailyPick": false
    },
    {
      "id": "match_2026_int_001",
      "league": "International Friendlies",
      "homeTeam": "Croatia",
      "awayTeam": "Colombia",
      "date": "2026-03-27",
      "time": "02:30",
      "prediction": {
        "mainPick": "Away Win",
        "odds": "1.86",
        "overUnder": "2.5 Over",
        "btts": "Yes",
        "predictedScore": "1-2",
        "corners": "11.5 Over",
        "cards": "3.5 Under",
        "confidence": 80
      },
      "analysis": "Colombia shows better momentum in neutral venues. Expect an offensive game with goals from both sides.",
      "result": "pending",
      "vip": false,
      "adUnlock": true,
      "isDailyPick": true
    },
    {
      "id": "match_2026_chi_001",
      "league": "Chile Copa de la Liga",
      "homeTeam": "Everton de Vina",
      "awayTeam": "O'Higgins",
      "date": "2026-03-27",
      "time": "02:30",
      "prediction": {
        "mainPick": "Home Win",
        "odds": "2.04",
        "overUnder": "2.5 Over",
        "btts": "Yes",
        "predictedScore": "2-1",
        "corners": "10.5 Over",
        "cards": "5.5 Over",
        "confidence": 75
      },
      "analysis": "Everton holds a strong home advantage. O'Higgins may score, but the hosts are expected to secure 3 points.",
      "result": "pending",
      "vip": false,
      "adUnlock": false,
      "isDailyPick": false
    },
    {
      "id": "match_2026_chi_002",
      "league": "Chile Copa de la Liga",
      "homeTeam": "Universidad Concepcion",
      "awayTeam": "Cobresal",
      "date": "2026-03-27",
      "time": "02:30",
      "prediction": {
        "mainPick": "Home Win",
        "odds": "1.65",
        "overUnder": "2.5 Over",
        "btts": "No",
        "predictedScore": "3-1",
        "corners": "9.5 Under",
        "cards": "4.5 Under",
        "confidence": 85
      },
      "analysis": "Concepcion is in superior form compared to Cobresal's struggling defense. Clear home win expected.",
      "result": "pending",
      "vip": true,
      "adUnlock": false,
      "isDailyPick": true
    },
    {
      "id": "match_2026_arg_001",
      "league": "Argentina Primera LFP - Apertura",
      "homeTeam": "Argentinos Juniors",
      "awayTeam": "Atletico Lanus",
      "date": "2026-03-27",
      "time": "03:00",
      "prediction": {
        "mainPick": "Home Win",
        "odds": "1.73",
        "overUnder": "2.5 Under",
        "btts": "No",
        "predictedScore": "2-0",
        "corners": "8.5 Under",
        "cards": "4.5 Over",
        "confidence": 80
      },
      "analysis": "Argentinos Juniors are disciplined at home. Lanus lacks offensive creativity in away matches.",
      "result": "pending",
      "vip": false,
      "adUnlock": false,
      "isDailyPick": false
    },
    {
      "id": "match_2026_int_002",
      "league": "International Friendlies",
      "homeTeam": "Dominican Republic",
      "awayTeam": "El Salvador",
      "date": "2026-03-27",
      "time": "03:00",
      "prediction": {
        "mainPick": "Draw",
        "odds": "2.90",
        "overUnder": "2.5 Under",
        "btts": "Yes",
        "predictedScore": "1-1",
        "corners": "9.5 Over",
        "cards": "3.5 Under",
        "confidence": 70
      },
      "analysis": "Friendly match between two evenly matched CONCACAF sides. A balanced draw is the most likely result.",
      "result": "pending",
      "vip": false,
      "adUnlock": true,
      "isDailyPick": false
    },
    {
      "id": "match_2026_int_003",
      "league": "International Friendlies",
      "homeTeam": "Chile",
      "awayTeam": "Cape Verde",
      "date": "2026-03-27",
      "time": "06:00",
      "prediction": {
        "mainPick": "Home Win",
        "odds": "1.56",
        "overUnder": "2.5 Under",
        "btts": "No",
        "predictedScore": "1-0",
        "corners": "8.5 Alt",
        "cards": "2.5 Alt",
        "confidence": 85
      },
      "analysis": "Chile is testing new players. Expect a low-tempo game where the hosts dominate possession.",
      "result": "pending",
      "vip": true,
      "adUnlock": false,
      "isDailyPick": true
    }
  ]
}
{
 
    {
      "id": "match_2026_aus_001",
      "league": "Australia NPL Victoria",
      "homeTeam": "Bentleigh Greens",
      "awayTeam": "Dandenong Thunder",
      "date": "2026-03-27",
      "time": "11:30",
      "prediction": {
        "mainPick": "Home Win",
        "odds": "2.04",
        "overUnder": "2.5 Over",
        "btts": "Yes",
        "predictedScore": "3-1",
        "corners": "12.5 Over",
        "cards": "4.5 Over",
        "confidence": 75
      },
      "analysis": "High intensity expected in the Victorian NPL. Both teams are prone to scoring and high corner counts.",
      "result": "pending",
      "vip": false,
      "adUnlock": true,
      "isDailyPick": false
    },
    {
      "id": "match_2026_aus_002",
      "league": "Australia NPL Victoria",
      "homeTeam": "Heidelberg United",
      "awayTeam": "Melbourne City U21",
      "date": "2026-03-27",
      "time": "11:30",
      "prediction": {
        "mainPick": "Home Win",
        "odds": "1.27",
        "overUnder": "2.5 Over",
        "btts": "No",
        "predictedScore": "4-0",
        "corners": "11.5 Over",
        "cards": "3.5 Under",
        "confidence": 95
      },
      "analysis": "Heidelberg is a title contender. The visitors' youth squad will likely struggle with the physical pressure.",
      "result": "pending",
      "vip": true,
      "adUnlock": false,
      "isDailyPick": true
    },
    {
      "id": "match_2026_u21_001",
      "league": "U21 Euro Championship Qualifiers",
      "homeTeam": "Georgia U21",
      "awayTeam": "Latvia U21",
      "date": "2026-03-27",
      "time": "18:00",
      "prediction": {
        "mainPick": "Home Win",
        "odds": "1.29",
        "overUnder": "2.5 Under",
        "btts": "No",
        "predictedScore": "2-0",
        "corners": "8.5 Under",
        "cards": "3.5 Under",
        "confidence": 95
      },
      "analysis": "Georgia's U21 side is highly organized. Latvia will struggle to break through their defensive line.",
      "result": "pending",
      "vip": true,
      "adUnlock": false,
      "isDailyPick": true
    },
    {
      "id": "match_2026_u21_002",
      "league": "U21 Euro Championship Qualifiers",
      "homeTeam": "Norway U21",
      "awayTeam": "Netherlands U21",
      "date": "2026-03-27",
      "time": "20:00",
      "prediction": {
        "mainPick": "Draw",
        "odds": "3.27",
        "overUnder": "2.5 Over",
        "btts": "Yes",
        "predictedScore": "2-2",
        "corners": "11.5 Over",
        "cards": "4.5 Over",
        "confidence": 75
      },
      "analysis": "Two offensive powerhouses meet. A high-scoring game and technical battle in the midfield is expected.",
      "result": "pending",
      "vip": false,
      "adUnlock": true,
      "isDailyPick": false
    },
    {
      "id": "match_2026_u21_003",
      "league": "U21 Euro Championship Qualifiers",
      "homeTeam": "Germany U21",
      "awayTeam": "Northern Ireland U21",
      "date": "2026-03-27",
      "time": "20:00",
      "prediction": {
        "mainPick": "Home Win",
        "odds": "1.12",
        "overUnder": "2.5 Over",
        "btts": "No",
        "predictedScore": "3-0",
        "corners": "10.5 Over",
        "cards": "3.5 Under",
        "confidence": 92
      },
      "analysis": "Germany is the absolute favorite. Expect total dominance and high corner numbers from the hosts.",
      "result": "pending",
      "vip": false,
      "adUnlock": false,
      "isDailyPick": true
    },
    {
      "id": "match_2026_fra_001",
      "league": "France National League",
      "homeTeam": "Fleury 91",
      "awayTeam": "Bourg-en-Bresse",
      "date": "2026-03-27",
      "time": "21:30",
      "prediction": {
        "mainPick": "Draw",
        "odds": "3.02",
        "overUnder": "2.5 Under",
        "btts": "Yes",
        "predictedScore": "1-1",
        "corners": "9.5 Over",
        "cards": "4.5 Over",
        "confidence": 70
      },
      "analysis": "Very balanced encounter. Both teams rely on counter-attacks which often leads to shared points.",
      "result": "pending",
      "vip": false,
      "adUnlock": false,
      "isDailyPick": true
    }
  ]
}
